granatum/__init__.py
granatum/granatum.py
granatum/utils.py
tests/__init__.py
tests/integration/__init__.py
tests/unit/__init__.py
tests/unit/test_granatum.py
tests/unit/test_utils.py
python_granatum-0.0.6.dist-info/LICENSE
python_granatum-0.0.6.dist-info/METADATA
python_granatum-0.0.6.dist-info/WHEEL
python_granatum-0.0.6.dist-info/top_level.txt
python_granatum-0.0.6.dist-info/RECORD
