Metadata-Version: 2.1
Name: python-granatum
Version: 0.0.6
Summary: A Python wrapper for Granatum Financeiro
Home-page: https://github.com/dustinglass/python-granatum
Author: dustintheglass
Author-email: dustin.glass@gmail.com
License: UNKNOWN
Platform: UNKNOWN
Classifier: Programming Language :: Python :: 3
Classifier: License :: OSI Approved :: MIT License
Classifier: Operating System :: OS Independent
Classifier: Topic :: Office/Business :: Financial :: Accounting
Requires-Python: >=3.6
Requires-Dist: lxml
Requires-Dist: pandas
Requires-Dist: python-dateutil
Requires-Dist: requests
